regcertipy/__init__.py
regcertipy/__main__.py
regcertipy/utils.py
regcertipy/models/__init__.py
regcertipy/models/cert_template.py
regcertipy/parsers/__init__.py
regcertipy/parsers/reg_bof_parser.py
regcertipy/parsers/regfile_parser.py
regcertipy-1.1.0.dist-info/METADATA
regcertipy-1.1.0.dist-info/WHEEL
regcertipy-1.1.0.dist-info/entry_points.txt
regcertipy-1.1.0.dist-info/licenses/LICENSE
regcertipy-1.1.0.dist-info/RECORD
