Metadata-Version: 2.4
Name: regcertipy
Version: 1.1.0
Summary: Parses cached certificate templates from a Windows Registry file and displays them in the same style as Certipy does.
Author-email: Max Grim <max@outflank.nl>, Cedric van Bockhaven <cedric@outflank.nl>
License-File: LICENSE
Requires-Python: >=3.12
Requires-Dist: certipy-ad==5.0.3
Requires-Dist: neo4j>=5.28.1
